odoo/addons/account_avatax_website_sale/README.rst
odoo/addons/account_avatax_website_sale/__init__.py
odoo/addons/account_avatax_website_sale/__manifest__.py
odoo/addons/account_avatax_website_sale/controllers/__init__.py
odoo/addons/account_avatax_website_sale/controllers/main.py
odoo/addons/account_avatax_website_sale/i18n/account_avatax_website_sale.pot
odoo/addons/account_avatax_website_sale/readme/CONTRIBUTORS.rst
odoo/addons/account_avatax_website_sale/readme/DESCRIPTION.rst
odoo/addons/account_avatax_website_sale/readme/USAGE.rst
odoo/addons/account_avatax_website_sale/static/description/icon.png
odoo/addons/account_avatax_website_sale/static/description/index.html
odoo14_addon_account_avatax_website_sale-14.0.2.0.0.dist-info/METADATA
odoo14_addon_account_avatax_website_sale-14.0.2.0.0.dist-info/WHEEL
odoo14_addon_account_avatax_website_sale-14.0.2.0.0.dist-info/top_level.txt
odoo14_addon_account_avatax_website_sale-14.0.2.0.0.dist-info/RECORD
